erdiagram/__init__.py
erdiagram/_sqlalchemy.py
erdiagram/_utils.py
erdiagram-0.1.3.dist-info/LICENSE
erdiagram-0.1.3.dist-info/WHEEL
erdiagram-0.1.3.dist-info/METADATA
erdiagram-0.1.3.dist-info/RECORD
