Metadata-Version: 2.1
Name: erdiagram
Version: 0.1.3
Summary: Make diagrams for SQLAlchemy.
Author-email: Lamin Labs <laminlabs@gmail.com>
Requires-Dist: pydot
Requires-Dist: sqlalchemy<2.0
Requires-Dist: pre-commit ; extra == "dev"
Requires-Dist: nox ; extra == "dev"
Requires-Dist: pytest>=6.0 ; extra == "test"
Requires-Dist: pytest-cov ; extra == "test"
Requires-Dist: nbmake ; extra == "test"
Project-URL: Home, https://github.com/laminlabs/erdiagram
Provides-Extra: dev
Provides-Extra: test
